django_lookbook/__init__.py
django_lookbook/app_settings.py
django_lookbook/apps.py
django_lookbook/fields.py
django_lookbook/preview.py
django_lookbook/static/lookbook/css/app.css
django_lookbook/static/lookbook/css/app.css.map
django_lookbook/static/lookbook/js/app.js
django_lookbook/static/lookbook/js/app.js.LICENSE.txt
django_lookbook/static/lookbook/js/app.js.map
django_lookbook/static/lookbook/manifest.json
django_lookbook/static/lookbook/vendors/.gitkeep
django_lookbook/static/lookbook/vendors/images/.gitkeep
django_lookbook/static/lookbook/vendors/images/lucide-sprite.svg
django_lookbook/static/lookbook/vendors/images/sample.jpg
django_lookbook/static/lookbook/vendors/images/webpack.png
django_lookbook/templates/django_lookbook/404.html
django_lookbook/templates/django_lookbook/base.html
django_lookbook/templates/django_lookbook/fields/toggle_switch_widget.html
django_lookbook/templates/django_lookbook/includes/sidebar_2_level.html
django_lookbook/templates/django_lookbook/includes/sidebar_3_level.html
django_lookbook/templates/django_lookbook/includes/sidebar_previews.html
django_lookbook/templates/django_lookbook/index.html
django_lookbook/templates/django_lookbook/inspect.html
django_lookbook/templates/django_lookbook/meta.html
django_lookbook/templates/django_lookbook/top_bar.html
django_lookbook/urls.py
django_lookbook/utils.py
django_lookbook/views.py
django_lookbook-1.0.2.dist-info/METADATA
django_lookbook-1.0.2.dist-info/WHEEL
django_lookbook-1.0.2.dist-info/RECORD
