Metadata-Version: 2.1
Name: django-lookbook
Version: 1.0.2
Summary: UI development environment for Django
Home-page: https://github.com/rails-inspire-django/django-lookbook
License: MIT
Author: Michael Yin
Author-email: michaelyin@accordbox.com
Requires-Python: >=3.8
Classifier: License :: OSI Approved :: MIT License
Classifier: Programming Language :: Python :: 3
Classifier: Programming Language :: Python :: 3.8
Classifier: Programming Language :: Python :: 3.9
Classifier: Programming Language :: Python :: 3.10
Classifier: Programming Language :: Python :: 3.11
Classifier: Programming Language :: Python :: 3.12
Requires-Dist: django (>=3.2)
Requires-Dist: django-viewcomponent (>=1.0.5)
Project-URL: Changelog, https://github.com/rails-inspire-django/django-lookbook/releases
